ipleak/__init__.py
ipleak/__main__.py
ipleak-0.3.3.dist-info/LICENSE
ipleak-0.3.3.dist-info/METADATA
ipleak-0.3.3.dist-info/WHEEL
ipleak-0.3.3.dist-info/entry_points.txt
ipleak-0.3.3.dist-info/top_level.txt
ipleak-0.3.3.dist-info/RECORD
