Metadata-Version: 2.1
Name: ipleak
Version: 0.3.3
Summary: Python Tool to check your VPN.
Home-page: https://github.com/ProfileID/ipleak
Author: profileid
Author-email: profileid@protonmail.com
License: MIT
Platform: UNKNOWN
Classifier: Programming Language :: Python :: 3.6
Classifier: Programming Language :: Python :: 3.7
Classifier: Programming Language :: Python :: 3.8
Requires-Dist: requests
Requires-Dist: click
Requires-Dist: typer
Requires-Dist: rich
